functions_framework/__init__.py
functions_framework/__main__.py
functions_framework/_cli.py
functions_framework/_function_registry.py
functions_framework/constants.py
functions_framework/exceptions.py
functions_framework/log.py
functions_framework/runner.py
functions_framework/context/__init__.py
functions_framework/context/function_context.py
functions_framework/context/runtime_context.py
functions_framework/context/user_context.py
functions_framework/openfunction/__init__.py
functions_framework/openfunction/function_out.py
functions_framework/triggers/__init__.py
functions_framework/triggers/trigger.py
functions_framework/triggers/dapr_trigger/__init__.py
functions_framework/triggers/dapr_trigger/dapr.py
functions_framework/triggers/http_trigger/__init__.py
functions_framework/triggers/http_trigger/http.py
functions_framework/triggers/http_trigger/_http/__init__.py
functions_framework/triggers/http_trigger/_http/flask.py
functions_framework/triggers/http_trigger/_http/gunicorn.py
ofn_functions_framework-0.2.0rc1.dist-info/LICENSE
ofn_functions_framework-0.2.0rc1.dist-info/METADATA
ofn_functions_framework-0.2.0rc1.dist-info/WHEEL
ofn_functions_framework-0.2.0rc1.dist-info/entry_points.txt
ofn_functions_framework-0.2.0rc1.dist-info/top_level.txt
ofn_functions_framework-0.2.0rc1.dist-info/RECORD
