Metadata-Version: 2.1
Name: ofn-functions-framework
Version: 0.2.0rc1
Summary: An open source FaaS (Function as a service) framework for writing portable Python functions.
Home-page: https://github.com/OpenFunction/functions-framework-python
Author: OpenFunction
Author-email: openfunction@kubesphere.io
Keywords: functions-framework
Classifier: Development Status :: 3 - Alpha
Classifier: Intended Audience :: Developers
Classifier: License :: OSI Approved :: Apache Software License
Classifier: Programming Language :: Python :: 3
Classifier: Programming Language :: Python :: 3.5
Classifier: Programming Language :: Python :: 3.6
Classifier: Programming Language :: Python :: 3.7
Classifier: Programming Language :: Python :: 3.8
Classifier: Programming Language :: Python :: 3.9
Classifier: Programming Language :: Python :: 3.10
Requires-Python: >=3.5, <4
License-File: LICENSE
Requires-Dist: grpcio ==1.54.2
Requires-Dist: flask <3.0,>=1.0
Requires-Dist: click <9.0,>=7.0
Requires-Dist: uvicorn >=0.22.0
Requires-Dist: cloudevents <2.0.0,>=1.2.0
Requires-Dist: dapr >=1.10.0
Requires-Dist: aiohttp ==3.8.5
Requires-Dist: dapr-ext-grpc >=1.10.0
Requires-Dist: dapr-ext-fastapi >=1.10.0
Requires-Dist: gunicorn <21.0,>=19.2.0 ; platform_system != "Windows"
